pycpd/__init__.py
pycpd/affine_registration.py
pycpd/deformable_registration.py
pycpd/emregistration.py
pycpd/rigid_registration.py
pycpd/utility.py
pycpd-2.0.0.dist-info/LICENSE
pycpd-2.0.0.dist-info/METADATA
pycpd-2.0.0.dist-info/WHEEL
pycpd-2.0.0.dist-info/top_level.txt
pycpd-2.0.0.dist-info/RECORD
