Metadata-Version: 1.1
Name: pycpd
Version: 2.0.0
Summary: Pure Numpy Implementation of the Coherent Point Drift Algorithm
Home-page: https://github.com/siavashk/pycpd
Author: Siavash Khallaghi
Author-email: siavashk@ece.ubc.ca
License: MIT
Keywords: image processing,point cloud,registration,mesh,surface
Platform: UNKNOWN
Classifier: Development Status :: 3 - Alpha
Classifier: License :: OSI Approved :: MIT License
Classifier: Programming Language :: Python :: 2.7
Classifier: Programming Language :: Python :: 3.4
Classifier: Programming Language :: Python :: 3.5
Classifier: Programming Language :: Python :: 3.6
Classifier: Topic :: Scientific/Engineering
